acdh_handle_pyutils/__init__.py
acdh_handle_pyutils/client.py
acdh_handle_pyutils-0.4.2.dist-info/LICENSE
acdh_handle_pyutils-0.4.2.dist-info/METADATA
acdh_handle_pyutils-0.4.2.dist-info/WHEEL
acdh_handle_pyutils-0.4.2.dist-info/entry_points.txt
acdh_handle_pyutils-0.4.2.dist-info/top_level.txt
acdh_handle_pyutils-0.4.2.dist-info/RECORD
