Metadata-Version: 2.1
Name: acdh-handle-pyutils
Version: 0.4.2
Summary: Utility functions to interact with handle.net API
Home-page: https://github.com/acdh-oeaw/acdh-handle-pyutils
Author: Peter Andorfer
Author-email: peter.andorfer@oeaw.ac.at
License: MIT
Keywords: acdh-handle-pyutils
Classifier: Development Status :: 2 - Pre-Alpha
Classifier: Intended Audience :: Developers
Classifier: License :: OSI Approved :: MIT License
Classifier: Natural Language :: English
Classifier: Programming Language :: Python :: 3
Classifier: Programming Language :: Python :: 3.7
Classifier: Programming Language :: Python :: 3.8
Requires-Python: >=3.7
License-File: LICENSE
Requires-Dist: requests (<3,>=2.20.0)
